planqk/quantum/client/__init__.py
planqk/quantum/client/_version.py
planqk/quantum/client/client.py
planqk/quantum/client/credentials.py
planqk/quantum/client/sdk/__init__.py
planqk/quantum/client/sdk/client.py
planqk/quantum/client/sdk/environment.py
planqk/quantum/client/sdk/backends/__init__.py
planqk/quantum/client/sdk/backends/client.py
planqk/quantum/client/sdk/backends/raw_client.py
planqk/quantum/client/sdk/core/__init__.py
planqk/quantum/client/sdk/core/api_error.py
planqk/quantum/client/sdk/core/client_wrapper.py
planqk/quantum/client/sdk/core/datetime_utils.py
planqk/quantum/client/sdk/core/file.py
planqk/quantum/client/sdk/core/force_multipart.py
planqk/quantum/client/sdk/core/http_client.py
planqk/quantum/client/sdk/core/http_response.py
planqk/quantum/client/sdk/core/jsonable_encoder.py
planqk/quantum/client/sdk/core/pydantic_utilities.py
planqk/quantum/client/sdk/core/query_encoder.py
planqk/quantum/client/sdk/core/remove_none_from_dict.py
planqk/quantum/client/sdk/core/request_options.py
planqk/quantum/client/sdk/core/serialization.py
planqk/quantum/client/sdk/core/http_sse/__init__.py
planqk/quantum/client/sdk/core/http_sse/_api.py
planqk/quantum/client/sdk/core/http_sse/_decoders.py
planqk/quantum/client/sdk/core/http_sse/_exceptions.py
planqk/quantum/client/sdk/core/http_sse/_models.py
planqk/quantum/client/sdk/errors/__init__.py
planqk/quantum/client/sdk/errors/forbidden_error.py
planqk/quantum/client/sdk/errors/internal_server_error.py
planqk/quantum/client/sdk/errors/not_found_error.py
planqk/quantum/client/sdk/errors/unauthorized_error.py
planqk/quantum/client/sdk/jobs/__init__.py
planqk/quantum/client/sdk/jobs/client.py
planqk/quantum/client/sdk/jobs/raw_client.py
planqk/quantum/client/sdk/jobs/types/__init__.py
planqk/quantum/client/sdk/jobs/types/create_job_request_input.py
planqk/quantum/client/sdk/jobs/types/create_job_request_input_format.py
planqk/quantum/client/sdk/jobs/types/create_job_request_input_params.py
planqk_quantum_client-1.1.1.dist-info/licenses/LICENSE
planqk_quantum_client-1.1.1.dist-info/METADATA
planqk_quantum_client-1.1.1.dist-info/WHEEL
planqk_quantum_client-1.1.1.dist-info/top_level.txt
planqk_quantum_client-1.1.1.dist-info/RECORD
