Metadata-Version: 2.4
Name: planqk-quantum-client
Version: 1.1.1
Summary: Client SDK to run workloads on quantum devices provided by the PLANQK Platform. .
Author-email: Kipu Quantum GmbH <info@kipu-quantum.com>
Maintainer-email: Sebastian Wagner <sebastian.wagner@kipu-quantum.com>
License:                                  Apache License
Project-URL: Homepage, https://kipu-quantum.com/platform
Project-URL: Documentation, https://docs.planqk.de
Project-URL: Repository, https://gitlab.com/planqk-foss/planqk-api-sdk
Project-URL: Issues, https://gitlab.com/planqk-foss/planqk-quantum-client/-/issues
Project-URL: Changelog, https://gitlab.com/planqk-foss/planqk-quantum-client/-/releases
Classifier: Programming Language :: Python :: 3
Classifier: License :: OSI Approved :: Apache Software License
Classifier: Operating System :: OS Independent
Requires-Python: >=3.11
License-File: LICENSE
Requires-Dist: pydantic<2.10,>=2.5.0
Requires-Dist: httpx>=0.28.1
Dynamic: license-file
